LICENSE.txt
README.md
setup.cfg
setup.py
src/social_apis/__init__.py
src/social_apis.egg-info/PKG-INFO
src/social_apis.egg-info/SOURCES.txt
src/social_apis.egg-info/dependency_links.txt
src/social_apis.egg-info/not-zip-safe
src/social_apis.egg-info/top_level.txt
src/social_apis/authentication/__init__.py
src/social_apis/authentication/auth.py
src/social_apis/exceptions/__init__.py
src/social_apis/exceptions/social_api_error.py
src/social_apis/exceptions/twitter_error.py
src/social_apis/networks/__init__.py
src/social_apis/networks/facebook.py
src/social_apis/networks/linkedin.py
src/social_apis/networks/network.py
src/social_apis/networks/twitter.py
src/social_apis/networks/twitter_v2.py
src/social_apis/networks/vkontakte.py
src/social_apis/utils/__init__.py
src/social_apis/utils/request_iterator.py