Metadata-Version: 2.1
Name: social-apis
Version: 1.0
Summary: Social APIs is a library providing an easy way to access Social Networks APIs.
Home-page: https://github.com/azavodov/social-apis
Author: Andrey Zavodov
Author-email: a.p.zavodov@gmail.com
License: MIT
Keywords: social networks API requests access automation
Platform: UNKNOWN
License-File: LICENSE.txt
